ASTParser/Parser.py
ASTParser/__init__.py
ASTParser/utils.py
ASTPARSER-0.0.1.dist-info/LICENSE
ASTPARSER-0.0.1.dist-info/METADATA
ASTPARSER-0.0.1.dist-info/WHEEL
ASTPARSER-0.0.1.dist-info/top_level.txt
ASTPARSER-0.0.1.dist-info/RECORD
