Metadata-Version: 2.1
Name: ASTPARSER
Version: 0.0.1
Summary: A high-performance AST parsing utility enabling multi-language support with JSON AST serialization, ideal for intelligent code analysis pipelines.
Author-email: Abinayasankar M <abinayasankar2004@gmail.com>
License: MIT License
Project-URL: Source, https://github.com/Abinayasankar-co/ASTParser
Classifier: Development Status :: 4 - Beta
Classifier: Intended Audience :: Developers
Classifier: Programming Language :: Python :: 3
Classifier: License :: OSI Approved :: MIT License
Requires-Python: >=3.9
License-File: LICENSE
Requires-Dist: tree-sitter
Requires-Dist: tree-sitter-javascript
Requires-Dist: tree-sitter-typescript
Requires-Dist: traceback
